sparcli/__init__.py
sparcli/capture.py
sparcli/context.py
sparcli/controller.py
sparcli/data.py
sparcli/render.py
sparcli-0.1.3.dist-info/WHEEL
sparcli-0.1.3.dist-info/METADATA
sparcli-0.1.3.dist-info/RECORD
