Metadata-Version: 2.1
Name: sparcli
Version: 0.1.3
Summary: Visualize metrics as text in real-time (sparklines)
Home-page: https://github.com/z0u/sparcli
License: MIT
Keywords: console,sparkline,data,visualization
Author: Alex Fraser
Author-email: alex.d.fraser@gmail.com
Requires-Python: >=3.6,<4.0
Classifier: Environment :: Console
Classifier: License :: OSI Approved :: MIT License
Classifier: Programming Language :: Python :: 3
Classifier: Programming Language :: Python :: 3.6
Classifier: Programming Language :: Python :: 3.7
Classifier: Programming Language :: Python :: 3.8
Classifier: Topic :: System :: Monitoring
Classifier: Topic :: System :: Shells
Classifier: Topic :: Terminals
Requires-Dist: numpy (>=1.18.1,<2.0.0)
Project-URL: Repository, https://github.com/z0u/sparcli
